{
  "namespaces": [
    "public"
  ],
  "name": "public",
  "tables": [
    {
      "columns": {
        "id": {
          "name": "id",
          "type": "varchar(255)",
          "unsigned": false,
          "autoincrement": false,
          "primary": false,
          "nullable": false,
          "mappedType": "string"
        },
        "username": {
          "name": "username",
          "type": "text",
          "unsigned": false,
          "autoincrement": false,
          "primary": false,
          "nullable": false,
          "mappedType": "text"
        },
        "email": {
          "name": "email",
          "type": "text",
          "unsigned": false,
          "autoincrement": false,
          "primary": false,
          "nullable": false,
          "mappedType": "text"
        },
        "password": {
          "name": "password",
          "type": "text",
          "unsigned": false,
          "autoincrement": false,
          "primary": false,
          "nullable": false,
          "mappedType": "text"
        },
        "created_at": {
          "name": "created_at",
          "type": "timestamptz(0)",
          "unsigned": false,
          "autoincrement": false,
          "primary": false,
          "nullable": false,
          "length": 6,
          "mappedType": "datetime"
        },
        "updated_at": {
          "name": "updated_at",
          "type": "timestamptz(0)",
          "unsigned": false,
          "autoincrement": false,
          "primary": false,
          "nullable": false,
          "length": 6,
          "mappedType": "datetime"
        }
      },
      "name": "user",
      "schema": "public",
      "indexes": [
        {
          "columnNames": [
            "username"
          ],
          "composite": false,
          "keyName": "user_username_unique",
          "primary": false,
          "unique": true
        },
        {
          "columnNames": [
            "email"
          ],
          "composite": false,
          "keyName": "user_email_unique",
          "primary": false,
          "unique": true
        },
        {
          "keyName": "user_pkey",
          "columnNames": [
            "id"
          ],
          "composite": false,
          "primary": true,
          "unique": true
        }
      ],
      "checks": [],
      "foreignKeys": {}
    },
    {
      "columns": {
        "id": {
          "name": "id",
          "type": "varchar(255)",
          "unsigned": false,
          "autoincrement": false,
          "primary": false,
          "nullable": false,
          "mappedType": "string"
        },
        "name": {
          "name": "name",
          "type": "text",
          "unsigned": false,
          "autoincrement": false,
          "primary": false,
          "nullable": false,
          "length": 30,
          "mappedType": "text"
        },
        "text": {
          "name": "text",
          "type": "text",
          "unsigned": false,
          "autoincrement": false,
          "primary": false,
          "nullable": false,
          "mappedType": "text"
        },
        "creator_id": {
          "name": "creator_id",
          "type": "varchar(255)",
          "unsigned": false,
          "autoincrement": false,
          "primary": false,
          "nullable": false,
          "mappedType": "string"
        },
        "created_at": {
          "name": "created_at",
          "type": "timestamptz(0)",
          "unsigned": false,
          "autoincrement": false,
          "primary": false,
          "nullable": false,
          "length": 6,
          "mappedType": "datetime"
        },
        "updated_at": {
          "name": "updated_at",
          "type": "timestamptz(0)",
          "unsigned": false,
          "autoincrement": false,
          "primary": false,
          "nullable": false,
          "length": 6,
          "mappedType": "datetime"
        }
      },
      "name": "sub_reddit",
      "schema": "public",
      "indexes": [
        {
          "columnNames": [
            "name"
          ],
          "composite": false,
          "keyName": "sub_reddit_name_unique",
          "primary": false,
          "unique": true
        },
        {
          "keyName": "sub_reddit_pkey",
          "columnNames": [
            "id"
          ],
          "composite": false,
          "primary": true,
          "unique": true
        }
      ],
      "checks": [],
      "foreignKeys": {
        "sub_reddit_creator_id_foreign": {
          "constraintName": "sub_reddit_creator_id_foreign",
          "columnNames": [
            "creator_id"
          ],
          "localTableName": "public.sub_reddit",
          "referencedColumnNames": [
            "id"
          ],
          "referencedTableName": "public.user",
          "updateRule": "cascade"
        }
      }
    },
    {
      "columns": {
        "id": {
          "name": "id",
          "type": "varchar(255)",
          "unsigned": false,
          "autoincrement": false,
          "primary": false,
          "nullable": false,
          "mappedType": "string"
        },
        "title": {
          "name": "title",
          "type": "text",
          "unsigned": false,
          "autoincrement": false,
          "primary": false,
          "nullable": false,
          "mappedType": "text"
        },
        "text": {
          "name": "text",
          "type": "text",
          "unsigned": false,
          "autoincrement": false,
          "primary": false,
          "nullable": false,
          "mappedType": "text"
        },
        "creator_id": {
          "name": "creator_id",
          "type": "varchar(255)",
          "unsigned": false,
          "autoincrement": false,
          "primary": false,
          "nullable": false,
          "mappedType": "string"
        },
        "sub_reddit_id": {
          "name": "sub_reddit_id",
          "type": "varchar(255)",
          "unsigned": false,
          "autoincrement": false,
          "primary": false,
          "nullable": false,
          "mappedType": "string"
        },
        "points": {
          "name": "points",
          "type": "int",
          "unsigned": false,
          "autoincrement": false,
          "primary": false,
          "nullable": false,
          "default": "0",
          "mappedType": "integer"
        },
        "created_at": {
          "name": "created_at",
          "type": "timestamptz(0)",
          "unsigned": false,
          "autoincrement": false,
          "primary": false,
          "nullable": false,
          "length": 6,
          "mappedType": "datetime"
        },
        "updated_at": {
          "name": "updated_at",
          "type": "timestamptz(0)",
          "unsigned": false,
          "autoincrement": false,
          "primary": false,
          "nullable": false,
          "length": 6,
          "mappedType": "datetime"
        }
      },
      "name": "post",
      "schema": "public",
      "indexes": [
        {
          "keyName": "post_pkey",
          "columnNames": [
            "id"
          ],
          "composite": false,
          "primary": true,
          "unique": true
        }
      ],
      "checks": [],
      "foreignKeys": {
        "post_creator_id_foreign": {
          "constraintName": "post_creator_id_foreign",
          "columnNames": [
            "creator_id"
          ],
          "localTableName": "public.post",
          "referencedColumnNames": [
            "id"
          ],
          "referencedTableName": "public.user",
          "updateRule": "cascade"
        },
        "post_sub_reddit_id_foreign": {
          "constraintName": "post_sub_reddit_id_foreign",
          "columnNames": [
            "sub_reddit_id"
          ],
          "localTableName": "public.post",
          "referencedColumnNames": [
            "id"
          ],
          "referencedTableName": "public.sub_reddit",
          "updateRule": "cascade"
        }
      }
    },
    {
      "columns": {
        "user_id": {
          "name": "user_id",
          "type": "varchar(255)",
          "unsigned": false,
          "autoincrement": false,
          "primary": false,
          "nullable": false,
          "mappedType": "string"
        },
        "sub_reddit_id": {
          "name": "sub_reddit_id",
          "type": "varchar(255)",
          "unsigned": false,
          "autoincrement": false,
          "primary": false,
          "nullable": false,
          "mappedType": "string"
        }
      },
      "name": "user_subscriptions",
      "schema": "public",
      "indexes": [
        {
          "keyName": "user_subscriptions_pkey",
          "columnNames": [
            "user_id",
            "sub_reddit_id"
          ],
          "composite": true,
          "primary": true,
          "unique": true
        }
      ],
      "checks": [],
      "foreignKeys": {
        "user_subscriptions_user_id_foreign": {
          "constraintName": "user_subscriptions_user_id_foreign",
          "columnNames": [
            "user_id"
          ],
          "localTableName": "public.user_subscriptions",
          "referencedColumnNames": [
            "id"
          ],
          "referencedTableName": "public.user",
          "deleteRule": "cascade",
          "updateRule": "cascade"
        },
        "user_subscriptions_sub_reddit_id_foreign": {
          "constraintName": "user_subscriptions_sub_reddit_id_foreign",
          "columnNames": [
            "sub_reddit_id"
          ],
          "localTableName": "public.user_subscriptions",
          "referencedColumnNames": [
            "id"
          ],
          "referencedTableName": "public.sub_reddit",
          "deleteRule": "cascade",
          "updateRule": "cascade"
        }
      }
    }
  ]
}
